ghgrenamer/__init__.py
ghgrenamer/_version.py
ghgrenamer/mappings.py
ghgrenamer-0.3.1.dist-info/LICENSE
ghgrenamer-0.3.1.dist-info/METADATA
ghgrenamer-0.3.1.dist-info/WHEEL
ghgrenamer-0.3.1.dist-info/top_level.txt
ghgrenamer-0.3.1.dist-info/RECORD
