Metadata-Version: 2.1
Name: ghgrenamer
Version: 0.3.1
Summary: Tool to rename GHG emissions or concentration names
Home-page: https://github.com/openclimatedata/ghgrenamer
Author: Robert Gieseke
Author-email: robert.gieseke@pik-potsdam.de
License: BSD
Platform: UNKNOWN
Classifier: Development Status :: 4 - Beta
Classifier: Intended Audience :: Developers
Classifier: Operating System :: OS Independent
Classifier: Programming Language :: Python :: 3.5
Classifier: Programming Language :: Python :: 3.6
Requires-Dist: normality (>=2.0.0)
